toolbox_events/__init__.py
toolbox_events/daemon_client.py
toolbox_events/events/__init__.py
toolbox_events/events/models.py
toolbox_events/events/sinks.py
toolbox_events/events/sources.py
toolbox_events/settings.py
toolbox_events-0.1.0.dist-info/WHEEL
toolbox_events-0.1.0.dist-info/METADATA
toolbox_events-0.1.0.dist-info/RECORD
