Metadata-Version: 2.3
Name: toolbox-events
Version: 0.1.0
Summary: A package for managing events in the toolbox
Author: eelcovdw
Author-email: eelcovdw <eelcovdw@gmail.com>
Requires-Dist: httpx>=0.28.1
Requires-Dist: loguru>=0.7.3
Requires-Dist: pydantic>=2.11.7
Requires-Dist: pydantic-settings>=2.10.1
Requires-Python: >=3.12
